proxyseller/__init__.py
proxyseller/_async.py
proxyseller/models.py
proxyseller-1.1.3.dist-info/LICENSE
proxyseller-1.1.3.dist-info/METADATA
proxyseller-1.1.3.dist-info/WHEEL
proxyseller-1.1.3.dist-info/top_level.txt
proxyseller-1.1.3.dist-info/RECORD
